tap_forem/__init__.py
tap_forem/__main__.py
tap_forem/client.py
tap_forem/streams.py
tap_forem/tap.py
tap_forem-0.5.3.dist-info/METADATA
tap_forem-0.5.3.dist-info/WHEEL
tap_forem-0.5.3.dist-info/entry_points.txt
tap_forem-0.5.3.dist-info/licenses/LICENSE
tap_forem-0.5.3.dist-info/RECORD
