Metadata-Version: 2.4
Name: tap-forem
Version: 0.5.3
Summary: `tap-forem` is a Singer tap for Forem, built with the Meltano SDK for Singer Taps.
Project-URL: Issue Tracker, https://github.com/reservoir-data/tap-forem/issues
Project-URL: Repository, https://github.com/reservoir-data/tap-forem
Author-email: Edgar Ramírez-Mondragón <edgarrm358@gmail.com>
Maintainer-email: Edgar Ramírez-Mondragón <edgarrm358@gmail.com>
License:                                  Apache License
License-File: LICENSE
Keywords: ELT,Forem,singer.io
Classifier: Programming Language :: Python :: 3 :: Only
Classifier: Programming Language :: Python :: 3.10
Classifier: Programming Language :: Python :: 3.11
Classifier: Programming Language :: Python :: 3.12
Classifier: Programming Language :: Python :: 3.13
Classifier: Programming Language :: Python :: 3.14
Requires-Python: >=3.10
Requires-Dist: singer-sdk~=0.51.0
